mplugins/myrrhc/pyro5_ext.py
mplugins/provider/pyro5/__doc__.py
mplugins/provider/pyro5/__init__.py
mplugins/provider/pyro5/__version__.py
mplugins/provider/pyro5/client.py
mplugins/provider/pyro5/config.py
mplugins/provider/pyro5/config_client.py
mplugins/provider/pyro5/config_server.py
mplugins/provider/pyro5/server.py
mplugins/scripts/myrrh_pyro5s.py
mplugin_provider_pyro5-0.1.0.dist-info/AUTHORS.md
mplugin_provider_pyro5-0.1.0.dist-info/LICENSE
mplugin_provider_pyro5-0.1.0.dist-info/METADATA
mplugin_provider_pyro5-0.1.0.dist-info/WHEEL
mplugin_provider_pyro5-0.1.0.dist-info/entry_points.txt
mplugin_provider_pyro5-0.1.0.dist-info/top_level.txt
mplugin_provider_pyro5-0.1.0.dist-info/RECORD
