Metadata-Version: 2.1
Name: mplugin_provider_pyro5
Version: 0.1.0
Summary: An agent for the myrrh porject using the pyro5 library
Author-email: PyAnjel7 <pyanjel7@gmail.com>
License: GNU GENERAL PUBLIC LICENSE
Project-URL: Source, https://github.com/pyanjel7/mplugin_provider_pyro5
Classifier: Environment :: Plugins
Classifier: Development Status :: 2 - Pre-Alpha
Classifier: Operating System :: Microsoft :: Windows
Classifier: Operating System :: POSIX
Classifier: Programming Language :: Python :: 3.11
Classifier: License :: OSI Approved :: GNU General Public License v3 or later (GPLv3+)
Classifier: Intended Audience :: Developers
Classifier: Intended Audience :: System Administrators
Classifier: Topic :: Software Development :: Libraries :: Python Modules
Classifier: Topic :: Software Development :: Testing
Classifier: Topic :: System :: Clustering
Classifier: Topic :: System :: Distributed Computing
Classifier: Topic :: System :: Monitoring
Classifier: Topic :: System :: Networking
Requires-Python: >=3.11.0
License-File: LICENSE
License-File: AUTHORS.md
Requires-Dist: pyro5 >=5.15
Requires-Dist: myrrh >=0.1.0
